LICENCE
MANIFEST.in
README.md
RELEASE-VERSION
pypi_description.rst
setup.py
version.py
OutputCheck/CheckFileParser.py
OutputCheck/CommentPrefixes.py
OutputCheck/Directives.py
OutputCheck/Driver.py
OutputCheck/FileChecker.py
OutputCheck/Utils.py
OutputCheck/__init__.py
OutputCheck.egg-info/PKG-INFO
OutputCheck.egg-info/SOURCES.txt
OutputCheck.egg-info/dependency_links.txt
OutputCheck.egg-info/entry_points.txt
OutputCheck.egg-info/top_level.txt