Metadata-Version: 1.1
Name: OutputCheck
Version: 0.4.1
Summary: A tool for checking the output of console programs inspired by LLVM's FileCheck
Home-page: https://github.com/stp/OutputCheck
Author: Daniel Liew
Author-email: delcypher@gmail.com
License: UNKNOWN
Platform: UNKNOWN
Classifier: Environment :: Console
Classifier: Development Status :: 3 - Alpha
Classifier: Intended Audience :: Developers
Classifier: License :: OSI Approved :: BSD License
Classifier: Natural Language :: English
Classifier: Operating System :: OS Independent
Classifier: Programming Language :: Python :: 2.7
Classifier: Programming Language :: Python :: 3
Classifier: Topic :: Software Development :: Testing
Classifier: Topic :: Text Processing
Classifier: Topic :: Utilities
